Metadata-Version: 2.1
Name: mddzgadnij
Version: 0.4.0
Summary: Tool that will try to guess your number
Author: Dawid Mielewczyk
Author-email: MDDawid0323@gmail.com
